pandora_plugin_libsgm/__init__.py
pandora_plugin_libsgm/abstract_sgm.py
pandora_plugin_libsgm/lib_3sgm.py
pandora_plugin_libsgm/lib_sgm.py
pandora_plugin_libsgm/penalty/__init__.py
pandora_plugin_libsgm/penalty/penalty.py
pandora_plugin_libsgm/penalty/penalty_mc_cnn.py
pandora_plugin_libsgm/penalty/penalty_sgm.py
pandora_plugin_libsgm-1.5.6.dist-info/licenses/LICENSE
tests/__init__.py
tests/common.py
tests/conftest.py
tests/disable_test_plugin_python_parall.py
tests/test_check_configuration.py
tests/test_lib3sgm.py
tests/test_libsgm.py
tests/test_penality_sgm.py
tests/test_penalty_mc_cnn.py
tests/test_plugin_python.py
pandora_plugin_libsgm-1.5.6.dist-info/METADATA
pandora_plugin_libsgm-1.5.6.dist-info/WHEEL
pandora_plugin_libsgm-1.5.6.dist-info/entry_points.txt
pandora_plugin_libsgm-1.5.6.dist-info/top_level.txt
pandora_plugin_libsgm-1.5.6.dist-info/RECORD
