Metadata-Version: 2.4
Name: pandora_plugin_libsgm
Version: 1.5.6
Summary: Pandora plugin to optimize the cost volume with the LibSGM library
Home-page: https://github.com/CNES/Pandora_plugin_libsgm
Author: CNES
Author-email: myriam.cournet@cnes.fr
License: Apache License 2.0
Requires-Python: >=3.8
License-File: LICENSE
Requires-Dist: numpy
Requires-Dist: rasterio
Requires-Dist: libsgm>=0.5.1
Requires-Dist: pandora==1.7.*
Requires-Dist: xarray
Requires-Dist: json-checker
Requires-Dist: importlib-metadata; python_version < "3.10"
Provides-Extra: dev
Requires-Dist: pytest; extra == "dev"
Requires-Dist: pytest-cov; extra == "dev"
Requires-Dist: pytest-resource-path; extra == "dev"
Requires-Dist: pylint; extra == "dev"
Requires-Dist: pre-commit; extra == "dev"
Requires-Dist: mypy; extra == "dev"
Requires-Dist: black; extra == "dev"
Requires-Dist: types-setuptools; extra == "dev"
Provides-Extra: docs
Requires-Dist: sphinx; extra == "docs"
Requires-Dist: sphinx_rtd_theme; extra == "docs"
Requires-Dist: sphinx_autoapi; extra == "docs"
Dynamic: description
Dynamic: license-file
